scoreplayer_external.py
scoreplayer_external-0.2.11.dist-info/COPYING
scoreplayer_external-0.2.11.dist-info/COPYING.LESSER
scoreplayer_external-0.2.11.dist-info/METADATA
scoreplayer_external-0.2.11.dist-info/WHEEL
scoreplayer_external-0.2.11.dist-info/top_level.txt
scoreplayer_external-0.2.11.dist-info/RECORD
