Metadata-Version: 2.1
Name: scoreplayer-external
Version: 0.2.11
Summary: Python external for controlling the Decibel ScorePlayer cavas mode
Home-page: http://www.decibelnewmusic.com/decibel-scoreplayer.html
Author: Aaron Wyatt
Author-email: python@psi-borg.org
License: UNKNOWN
Platform: UNKNOWN
Classifier: Development Status :: 3 - Alpha
Classifier: License :: OSI Approved :: GNU Lesser General Public License v3 or later (LGPLv3+)
Classifier: Programming Language :: Python :: 3
Classifier: Operating System :: MacOS :: MacOS X
Classifier: Operating System :: POSIX
Classifier: Operating System :: POSIX :: Linux
License-File: COPYING
License-File: COPYING.LESSER
Requires-Dist: zeroconf
Requires-Dist: python-osc
